{
  "meta": {
    "code": 200,
    "requestId": "5ed725a8660a9f001b0b6eaa"
  },
  "response": {
    "venue": {
      "id": "5bb6c8db610f04002c0a3690",
      "name": "Pagliacci Pizza",
      "contact": {
        "twitter": "pagaliccipizza",
        "instagram": "pagaliccipizza"
      },
      "location": {
        "address": "22830 NE 8th St Ste 101 Bldg 3",
        "lat": 47.61686819421978,
        "lng": -122.03469386261581,
        "labeledLatLngs": [
          {
            "label": "display",
            "lat": 47.61686819421978,
            "lng": -122.03469386261581
          }
        ],
        "postalCode": "98074",
        "cc": "US",
        "city": "Sammamish",
        "state": "WA",
        "country": "United States",
        "formattedAddress": [
          "22830 NE 8th St Ste 101 Bldg 3",
          "Sammamish, WA 98074",
          "United States"
        ]
      },
      "canonicalUrl": "https://foursquare.com/v/pagliacci-pizza/5bb6c8db610f04002c0a3690",
      "categories": [
        {
          "id": "4bf58dd8d48988d1ca941735",
          "name": "Pizza Place",
          "pluralName": "Pizza Places",
          "shortName": "Pizza",
          "icon": {
            "prefix": "https://ss3.4sqi.net/img/categories_v2/food/pizza_",
            "suffix": ".png"
          },
          "primary": true
        }
      ],
      "verified": false,
      "stats": {
        "tipCount": 0
      },
      "url": "http://www.pagalicci.com",
      "price": {
        "tier": 1,
        "message": "Cheap",
        "currency": "$"
      },
      "likes": {
        "count": 3,
        "groups": [
          {
            "type": "others",
            "count": 3,
            "items": [
              {
                "id": "130494",
                "firstName": "Phill",
                "lastName": "R",
                "photo": {
                  "prefix": "https://fastly.4sqi.net/img/user/",
                  "suffix": "/130494_OXR57JpQ_ilh0AMZlOL4NZl5V5LPWEQ0nTNpwbZ6XtrNyTE_ARbo5TmxUN8jMO-Dact8ZJpF6"
                }
              },
              {
                "id": "43073",
                "firstName": "Gerardo",
                "lastName": "V",
                "photo": {
                  "prefix": "https://fastly.4sqi.net/img/user/",
                  "suffix": "/5FS3BQ1YOANB4BY1.jpg"
                }
              },
              {
                "id": "48357",
                "firstName": "SE",
                "lastName": "B",
                "photo": {
                  "prefix": "https://fastly.4sqi.net/img/user/",
                  "suffix": "/48357_ekiq1RU8_K8kYws6gl5MGDd8hYslYAwfxdwc8sZpkalK4c-m_h0OlopbAgg883r4O1DLn_phG.jpg"
                }
              }
            ]
          }
        ],
        "summary": "3 Likes"
      },
      "dislike": false,
      "ok": false,
      "allowMenuUrlEdit": true,
      "beenHere": {
        "count": 0,
        "unconfirmedCount": 0,
        "marked": false,
        "lastCheckinExpiredAt": 0
      },
      "specials": {
        "count": 0,
        "items": []
      },
      "photos": {
        "count": 3,
        "groups": [
          {
            "type": "venue",
            "name": "Venue photos",
            "count": 3,
            "items": [
              {
                "id": "5d3a18dabfee6b0007a77636",
                "createdAt": 1564088538,
                "source": {
                  "name": "Swarm for iOS",
                  "url": "https://www.swarmapp.com"
                },
                "prefix": "https://fastly.4sqi.net/img/general/",
                "suffix": "/703793_D4w5s0kBqCf8ZGjF_JfoNF1moXW4AX_i77sGMGp2uok.jpg",
                "width": 1440,
                "height": 1920,
                "user": {
                  "id": "703793",
                  "firstName": "Michael",
                  "lastName": "P",
                  "photo": {
                    "prefix": "https://fastly.4sqi.net/img/user/",
                    "suffix": "/703793-S4Z0AEDRUSC4DBEH"
                  }
                },
                "visibility": "public"
              }
            ]
          }
        ]
      },
      "reasons": {
        "count": 0,
        "items": []
      },
      "hereNow": {
        "count": 0,
        "summary": "Nobody here",
        "groups": []
      },
      "createdAt": 1538705627,
      "tips": {
        "count": 0,
        "groups": [
          {
            "type": "others",
            "name": "All tips",
            "count": 0,
            "items": []
          }
        ]
      },
      "shortUrl": "https://4sq.com/2RnK1vw",
      "timeZone": "America/Los_Angeles",
      "listed": {
        "count": 0,
        "groups": [
          {
            "type": "others",
            "name": "Lists from other people",
            "count": 0,
            "items": []
          }
        ]
      },
      "seasonalHours": [],
      "pageUpdates": {
        "count": 0,
        "items": []
      },
      "inbox": {
        "count": 0,
        "items": []
      },
      "attributes": {
        "groups": [
          {
            "type": "price",
            "name": "Price",
            "summary": "$",
            "count": 1,
            "items": [
              {
                "displayName": "Price",
                "displayValue": "$",
                "priceTier": 1
              }
            ]
          },
          {
            "type": "payments",
            "name": "Credit Cards",
            "summary": "Credit Cards",
            "count": 7,
            "items": [
              {
                "displayName": "Credit Cards",
                "displayValue": "Yes"
              }
            ]
          },
          {
            "type": "serves",
            "name": "Menus",
            "summary": "Dinner, Lunch & more",
            "count": 8,
            "items": [
              {
                "displayName": "Brunch",
                "displayValue": "Brunch"
              },
              {
                "displayName": "Lunch",
                "displayValue": "Lunch"
              },
              {
                "displayName": "Dinner",
                "displayValue": "Dinner"
              }
            ]
          }
        ]
      },
      "bestPhoto": {
        "id": "5d3a18dabfee6b0007a77636",
        "createdAt": 1564088538,
        "source": {
          "name": "Swarm for iOS",
          "url": "https://www.swarmapp.com"
        },
        "prefix": "https://fastly.4sqi.net/img/general/",
        "suffix": "/703793_D4w5s0kBqCf8ZGjF_JfoNF1moXW4AX_i77sGMGp2uok.jpg",
        "width": 1440,
        "height": 1920,
        "visibility": "public"
      },
      "colors": {
        "highlightColor": {
          "photoId": "5d3a18dabfee6b0007a77636",
          "value": -12042176
        },
        "highlightTextColor": {
          "photoId": "5d3a18dabfee6b0007a77636",
          "value": -1
        },
        "algoVersion": 3
      }
    }
  }
}